cookiecutter_science_project_demo_repo/__init__.py
cookiecutter_science_project_demo_repo/_version.py
cookiecutter_science_project_demo_repo/dummy.py
cookiecutter_science_project_demo_repo-0.1.4.dist-info/LICENSE.txt
cookiecutter_science_project_demo_repo-0.1.4.dist-info/METADATA
cookiecutter_science_project_demo_repo-0.1.4.dist-info/WHEEL
cookiecutter_science_project_demo_repo-0.1.4.dist-info/top_level.txt
cookiecutter_science_project_demo_repo-0.1.4.dist-info/RECORD
