Metadata-Version: 2.1
Name: cookiecutter-science-project-demo-repo
Version: 0.1.4
Summary: Testing for cookiecutter template
Home-page: https://github.com/jbusecke/cookiecutter-science-project_demo_repo
Author: Julius Busecke
Author-email: AUTHOR@EMAIL.COM
License: BSD-3-Clause
Platform: UNKNOWN
Classifier: Development Status :: 5 - Production/Stable
Classifier: Topic :: Scientific/Engineering
Classifier: Intended Audience :: Science/Research
Classifier: Operating System :: OS Independent
Classifier: Programming Language :: Python
Classifier: Programming Language :: Python :: 3
Classifier: Programming Language :: Python :: 3.6
Classifier: Programming Language :: Python :: 3.7
Classifier: Programming Language :: Python :: 3.8
Classifier: License :: OSI Approved :: BSD License
Requires-Python: >=3.6
Requires-Dist: numpy
Requires-Dist: requests
